sebae/__init__.py
sebae/core/__init__.py
sebae/core/console/__init__.py
sebae/core/console/console.py
sebae/core/console/main.py
sebae/core/deployer/__init__.py
sebae/core/deployer/base.py
sebae/core/deployer/deployer_pybind11.py
sebae/templates/cffi/desc.toml
sebae/templates/cffi/setup.py
sebae/templates/common/pyproject.toml
sebae/templates/common/setup.cfg
sebae/templates/cpython/desc.toml
sebae/templates/cpython/setup.py
sebae/templates/cython/desc.toml
sebae/templates/cython/setup.py
sebae/templates/pybind11/CMakeLists.txt
sebae/templates/pybind11/README.md
sebae/templates/pybind11/algo.h
sebae/templates/pybind11/binding.cc
sebae/templates/pybind11/desc.toml
sebae/templates/pybind11/main.cc
sebae/templates/pybind11/setup.cfg
sebae/templates/pybind11/setup.py
sebae/templates/pybind11/pybind11/CMakeLists.txt
sebae/templates/pybind11/pybind11/tools/FindCatch.cmake
sebae/templates/pybind11/pybind11/tools/FindEigen3.cmake
sebae/templates/pybind11/pybind11/tools/FindPythonLibsNew.cmake
sebae/templates/pybind11/pybind11/tools/check-style.sh
sebae/templates/pybind11/pybind11/tools/libsize.py
sebae/templates/pybind11/pybind11/tools/mkdoc.py
sebae/templates/pybind11/pybind11/tools/pybind11Config.cmake.in
sebae/templates/pybind11/pybind11/tools/pybind11Tools.cmake
sebae/templates/swig/desc.toml
sebae/templates/swig/setup.py
sebae-0.1.4.dist-info/LICENSE
sebae-0.1.4.dist-info/METADATA
sebae-0.1.4.dist-info/WHEEL
sebae-0.1.4.dist-info/entry_points.txt
sebae-0.1.4.dist-info/top_level.txt
sebae-0.1.4.dist-info/RECORD
