Metadata-Version: 2.1
Name: sebae
Version: 0.1.4
Summary: Boilerplate tool for Python C/C++ extension
Home-page: https://github.com/actcwlf/sebae
Author: actcwlf
Author-email: actcwlf@163.com
License: MIT
Platform: UNKNOWN
Requires-Python: >=3.6
Requires-Dist: pybind11
Requires-Dist: cleo
